vtree/__init__.py
vtree/ipc.py
vtree/main.py
vtree_tree-2.4.0.dist-info/licenses/LICENSE
vtree_tree-2.4.0.dist-info/METADATA
vtree_tree-2.4.0.dist-info/WHEEL
vtree_tree-2.4.0.dist-info/entry_points.txt
vtree_tree-2.4.0.dist-info/top_level.txt
vtree_tree-2.4.0.dist-info/RECORD
